LICENSE
setup.py
macroplot/__init__.py
macroplot/link.py
macroplot/utils.py
macroplot_python.egg-info/PKG-INFO
macroplot_python.egg-info/SOURCES.txt
macroplot_python.egg-info/dependency_links.txt
macroplot_python.egg-info/not-zip-safe
macroplot_python.egg-info/requires.txt
macroplot_python.egg-info/top_level.txt