Metadata-Version: 2.1
Name: macroplot-python
Version: 1.1
Summary: Macroplot Python Client
Home-page: https://macroplot.com
Author: Sebastian Nogara
Author-email: snogara@macroplot.com
License: MIT
Classifier: Development Status :: 3 - Alpha
Classifier: Intended Audience :: Developers
Classifier: License :: OSI Approved :: MIT License
Classifier: Programming Language :: Python :: 3
Classifier: Programming Language :: Python :: 2
License-File: LICENSE
